[
  {
    "p": "Du skall icke spoila",
    "cite": "De bio budorden : 1"
  },
  {
    "p": "Låt din nästa se på bio såsom du själv skulle vilja se på bio",
    "cite": "De bio budorden : 2"
  },
  {
    "p": "Du skall icke späda din cola",
    "cite": "De bio budorden : 3"
  },
  {
    "p": "Det skall alltid finnas något att nomma på",
    "cite": "De bio budorden : 4"
  },
  {
    "p": "Du skola icke låta teoretiska biopoäng gå till spillo",
    "cite": "De bio budorden : 5"
  },
  {
    "p": "Du skall inga andra biogudar hava vid sidan av mig",
    "cite": "De bio budorden : 6"
  },
  {
    "p": "Du skall offra vart hundrade popcorn till din nästa",
    "cite": "De bio budorden : 7"
  },
  {
    "p": "Tänk på biodagen så att du helgar den",
    "cite": "De bio budorden : 8"
  },
  {
    "p": "Du skall icke stjäla din grannes popcorn utan vänta tryggt på ditt hundrade",
    "cite": "De bio budorden : 9"
  },
  {
    "p": "Du skall icke frestas av 3D, ty det är djävulens påfund",
    "cite": "De bio budorden : 10"
  },
  {
    "p": "Tag icke med en bebis",
    "cite": "De bio budorden : 37"
  }
]